3er Año/Organizacion de las computadoras/Tema 3 - Microarquitecturas del procesador/Guia practica 6/04_DM/DM.v
/*
4) memoria de datos
nombre: DM
ent: clk, addressDM(5), weD
sal: rd(32)
*/
module DM (
    input wire clk,                  // Señal de reloj
    input wire [4:0] addressDM,      // Dirección de la memoria (5 bits)
    input wire we,                   // Señal de habilitación de escritura
    input wire [31:0] wd,            // Dato a escribir (32 bits)
    output reg [31:0] rd             // Dato leído (32 bits)
);

// Declaración de la memoria de datos: 32 registros de 32 bits
reg [31:0] memory [0:31];

// Proceso de escritura
always @(posedge clk) begin
    if (we) begin
        memory[addressDM] <= wd; // Escribir el dato wd en la dirección especificada
    end
end

// Proceso de lectura
always @(*) begin
    rd = memory[addressDM];     // Leer el dato de la dirección especificada
end

endmodule

3er Año/Organizacion de las computadoras/Tema 3 - Microarquitecturas del procesador/Guia practica 7/memory/04_DM/DM_tb.v
`timescale 1ns / 1ps
`define DUMPSTR(x) `"x.vcd`"

module DM_tb();

    reg clk;                      // Señal de reloj
    reg [4:0] addressDM;           // Dirección de memoria de 5 bits
    reg we;                        // Señal de habilitación de escritura
    reg [31:0] wd;                 // Dato a escribir (32 bits)
    wire [31:0] rd;                // Dato leído (32 bits)

    // Instancia del módulo DM
    DM UUT (
        .clk(clk),
        .addressDM(addressDM),
        .we(we),
        .wd(wd),
        .rd(rd)
    );

    // Generador de reloj: cambia el estado cada 5 unidades de tiempo
    always #5 clk = ~clk;

    initial begin
        $dumpfile(`DUMPSTR(`VCD_OUTPUT));  // Archivo para almacenar los resultados de la simulación
        $dumpvars(0, DM_tb);               // Volcado de todas las variables

        // Inicialización
        clk = 0;
        we = 0;
        wd = 0;
        addressDM = 5'b00000;  // Dirección inicial
        
        // Escribir el valor 32'hAAAA_AAAA en la dirección 0
        #10;
        addressDM = 5'b00000;
        wd = 32'hAAAA_AAAA;
        we = 1;
        #10;
        
        // Escribir el valor 32'hBBBB_BBBB en la dirección 1
        addressDM = 5'b00001;
        wd = 32'hBBBB_BBBB;
        #10;
        
        // Desactivar escritura y leer de la dirección 0
        we = 0;
        addressDM = 5'b00000;
        #10;
        $display("Lectura de direccion 0: %h", rd);
        
        // Leer de la dirección 1
        addressDM = 5'b00001;
        #10;
        $display("Lectura de direccion 1: %h", rd);

        // Escribir el valor 32'hCCCC_CCCC en la dirección 2
        addressDM = 5'b00010;
        wd = 32'hCCCC_CCCC;
        we = 1;
        #10;

        // Leer de la dirección 2
        we = 0;
        addressDM = 5'b00010;
        #10;
        $display("Lectura de direccion 2: %h", rd);

        // Finalizar la simulación
        $finish;
    end

endmodule

3er Año/Organizacion de las computadoras/Tema 3 - Microarquitecturas del procesador/Guia practica 7/memory/04_DM/DM_tb.vcd
$date
	Fri Oct 04 17:43:14 2024
$end
$version
	Icarus Verilog
$end
$timescale
	1ps
$end
$scope module DM_tb $end
$var wire 32 ! rd [31:0] $end
$var reg 5 " addressDM [4:0] $end
$var reg 1 # clk $end
$var reg 32 $ wd [31:0] $end
$var reg 1 % we $end
$scope module UUT $end
$var wire 5 & addressDM [4:0] $end
$var wire 1 # clk $end
$var wire 32 ' wd [31:0] $end
$var wire 1 % we $end
$var reg 32 ( rd [31:0] $end
$upscope $end
$upscope $end
$enddefinitions $end
#0
$dumpvars
bx (
b0 '
b0 &
0%
b0 $
0#
b0 "
bx !
$end
#5000
1#
#10000
0#
1%
b10101010101010101010101010101010 $
b10101010101010101010101010101010 '
#15000
b10101010101010101010101010101010 !
b10101010101010101010101010101010 (
1#
#20000
bx !
bx (
0#
b10111011101110111011101110111011 $
b10111011101110111011101110111011 '
b1 "
b1 &
#25000
b10111011101110111011101110111011 !
b10111011101110111011101110111011 (
1#
#30000
b10101010101010101010101010101010 !
b10101010101010101010101010101010 (
0#
b0 "
b0 &
0%
#35000
1#
#40000
b10111011101110111011101110111011 !
b10111011101110111011101110111011 (
0#
b1 "
b1 &
#45000
1#
#50000
bx !
bx (
0#
1%
b11001100110011001100110011001100 $
b11001100110011001100110011001100 '
b10 "
b10 &
#55000
b11001100110011001100110011001100 !
b11001100110011001100110011001100 (
1#
#60000
0#
0%
