3er Año/Organizacion de las computadoras/Tema 3 - Microarquitecturas del procesador/Guia practica 7/dataPath/01_PC/PC.v
module PC(
    input wire clk,
    input wire [31:0] pcNext,
    output reg [31:0] pc
);

always @(posedge clk)
    begin
        pc <= pcNext;
    end
endmodule

3er Año/Organizacion de las computadoras/Tema 3 - Microarquitecturas del procesador/Guia practica 6/01_PC/PC_tb.v
`default_nettype none
`define DUMPSTR(x) `"x.vcd`"
`timescale 100 ns / 10 ns

module PC_tb;

    reg clk;              // Señal de reloj
    reg [31:0] pcNext;    // Próximo valor del contador de programa
    wire [31:0] pc;       // Salida del PC

    // Instancia del módulo PC
    PC uut(
        .clk(clk),
        .pcNext(pcNext),
        .pc(pc)
    );

    // Generador de la señal de reloj
    initial begin
        clk = 0;
        forever #5 clk = ~clk;  // Reloj con periodo de 10 unidades de tiempo
    end

    // Procedimiento de prueba
    initial begin
        // Archivos de volcado para la simulación en VCD
        $dumpfile(`DUMPSTR(`VCD_OUTPUT));
        $dumpvars(0, PC_tb);

        // Inicializa las señales
        pcNext = 32'h00000000;

        // Espera algunos ciclos y prueba varios valores
        #10;
        pcNext = 32'h00000010;  // Prueba con un valor
        #10;
        pcNext = 32'h00000020;  // Prueba con otro valor
        #10;
        pcNext = 32'h000000FF;  // Prueba con otro valor
        #10;
        pcNext = 32'h0000FFFF;  // Prueba con otro valor

        // Termina la simulación
        #50 $display("End of simulation");
        $finish;
    end
endmodule

3er Año/Organizacion de las computadoras/Tema 3 - Microarquitecturas del procesador/Guia practica 7/dataPath/01_PC/PC_tb.vcd
$date
	Tue Oct 01 10:05:38 2024
$end
$version
	Icarus Verilog
$end
$timescale
	1ps
$end
$scope module PC_tb $end
$var wire 32 ! pc [31:0] $end
$var reg 1 " clk $end
$var reg 32 # pcNext [31:0] $end
$scope module uut $end
$var wire 1 " clk $end
$var wire 32 $ pcNext [31:0] $end
$var reg 32 % pc [31:0] $end
$upscope $end
$upscope $end
$enddefinitions $end
$comment Show the parameter values. $end
$dumpall
$end
#0
$dumpvars
bx %
b0 $
b0 #
0"
bx !
$end
#500000
b0 !
b0 %
1"
#1000000
0"
b10000 #
b10000 $
#1500000
b10000 !
b10000 %
1"
#2000000
0"
b100000 #
b100000 $
#2500000
b100000 !
b100000 %
1"
#3000000
0"
b11111111 #
b11111111 $
#3500000
b11111111 !
b11111111 %
1"
#4000000
0"
b1111111111111111 #
b1111111111111111 $
#4500000
b1111111111111111 !
b1111111111111111 %
1"
