3er Año/Organizacion de las computadoras/Tema 3 - Microarquitecturas del procesador/Guia practica 6/05_SE/SE.v
module SE (
    input wire [24:0] inm, // Entrada de 25 bits de la instrucción
    input wire [1:0] src,  // Selector de la instrucción (I, S, B, U, J)
    output reg [31:0] inmExt // Salida extendida a 32 bits
);

always @(*) begin
    case (src)
        2'b00: begin // Tipo I
            inmExt = {{20{inm[24]}}, inm[24:13]};
        end
        2'b01: begin // Tipo S
            inmExt = {{20{inm[24]}}, inm[24:18], inm[10:7]};
        end
        2'b10: begin // Tipo B
            inmExt = {{19{inm[24]}}, inm[24], inm[23:18], inm[10:8], inm[7]};
        end
        2'b11: begin // Tipo U
            inmExt = {inm[24:13], 12'b0};
        end
        3'b100: begin // Tipo J
            inmExt = {{11{inm[24]}}, inm[23:14], inm[13], inm[12:8], inm[7:4]};
        end
        default: inmExt = 32'b0;
    endcase
end

endmodule

3er Año/Organizacion de las computadoras/Tema 3 - Microarquitecturas del procesador/Guia practica 7/dataPath/05_SE/SE_tb.v
`timescale 1ns / 1ps
`define DUMPSTR(x) `"x.vcd`"

module SE_tb();

    reg [24:0] inm;    // Entrada inmediata de 25 bits
    reg [1:0] src;     // Selector de instrucción
    wire [31:0] inmExt; // Salida extendida a 32 bits

    // Instanciamos el módulo SE
    SE UUT (
        .inm(inm),
        .src(src),
        .inmExt(inmExt)
    );

    // Bloque inicial de prueba
    initial begin
        $dumpfile(`DUMPSTR(`VCD_OUTPUT));  // Archivo de volcado de la simulación
        $dumpvars(0, SE_tb);               // Volcado de todas las variables

        // Prueba Tipo I
        inm = 25'b0000000000000000000000000; src = 2'b00; #1;
        $display("Tipo I: inm = %b, src = %b, inmExt = %b", inm, src, inmExt);

        inm = 25'b1000000000000000000000000; src = 2'b00; #1;
        $display("Tipo I: inm = %b, src = %b, inmExt = %b", inm, src, inmExt);

        // Prueba Tipo S
        inm = 25'b0000000000000000000000000; src = 2'b01; #1;
        $display("Tipo S: inm = %b, src = %b, inmExt = %b", inm, src, inmExt);

        inm = 25'b1111111111111111111111111; src = 2'b01; #1;
        $display("Tipo S: inm = %b, src = %b, inmExt = %b", inm, src, inmExt);

        // Prueba Tipo B
        inm = 25'b0000000000000000000000000; src = 2'b10; #1;
        $display("Tipo B: inm = %b, src = %b, inmExt = %b", inm, src, inmExt);

        inm = 25'b1010101010101010101010101; src = 2'b10; #1;
        $display("Tipo B: inm = %b, src = %b, inmExt = %b", inm, src, inmExt);

        // Prueba Tipo U
        inm = 25'b0000000000000000000000000; src = 2'b11; #1;
        $display("Tipo U: inm = %b, src = %b, inmExt = %b", inm, src, inmExt);

        inm = 25'b1111111111111111111111111; src = 2'b11; #1;
        $display("Tipo U: inm = %b, src = %b, inmExt = %b", inm, src, inmExt);

        // Finalizar la simulación
        $finish;
    end

endmodule

3er Año/Organizacion de las computadoras/Tema 3 - Microarquitecturas del procesador/Guia practica 7/dataPath/05_SE/SE_tb.vcd
$date
	Tue Oct 22 12:41:36 2024
$end
$version
	Icarus Verilog
$end
$timescale
	1ps
$end
$scope module SE_tb $end
$var wire 32 ! inmExt [31:0] $end
$var reg 25 " inm [24:0] $end
$var reg 2 # src [1:0] $end
$scope module UUT $end
$var wire 25 $ inm [24:0] $end
$var wire 2 % src [1:0] $end
$var reg 32 & inmExt [31:0] $end
$upscope $end
$upscope $end
$enddefinitions $end
$comment Show the parameter values. $end
$dumpall
$end
#0
$dumpvars
b0 &
b0 %
b0 $
b0 #
b0 "
b0 !
$end
#1000
b11111111111111111111100000000000 !
b11111111111111111111100000000000 &
b1000000000000000000000000 "
b1000000000000000000000000 $
#2000
b0 !
b0 &
b1 #
b1 %
b0 "
b0 $
#3000
b1111111111111111111111111111111 !
b1111111111111111111111111111111 &
b1111111111111111111111111 "
b1111111111111111111111111 $
#4000
b0 !
b0 &
b10 #
b10 %
b0 "
b0 $
#5000
b111111111111111111110101011010 !
b111111111111111111110101011010 &
b1010101010101010101010101 "
b1010101010101010101010101 $
#6000
b0 !
b0 &
b11 #
b11 %
b0 "
b0 $
#7000
b111111111111000000000000 !
b111111111111000000000000 &
b1111111111111111111111111 "
b1111111111111111111111111 $
